<package>
  <description brief="droneVisualMarkersLocalizerROSModule">

     droneVisualMarkersLocalizerROSModule

  </description>
  <author>Paloma de la Puente and Jose Luis Sánchez López</author>
  <license>BSD</license>
  <review status="unreviewed" notes=""/>
  <url>http://ros.org/wiki/droneVisualMarkersLocalizerROSModule</url>
  
  <depend package="roscpp"/>
  <depend package="std_msgs"/>
  <depend package="droneMsgsROS"/>
  <depend package="droneModuleROS"/>
  
  <depend package="droneVisualMarkersLocalizer"/>
  
  <depend package="referenceFramesROS"/>
  <depend package="lib_cvgutils"/>
  
  
  
  
  <!--
  <export>
  	<cpp cflags="-I${prefix}/src/include" lflags="-L${prefix}/lib -ldroneVisualMarkersLocalizerROSModule"/>
  </export>
  -->


</package>


